[
  {"section":"Reading","path":"Reading/manuscript/manuscript.html","name":"manuscript.html","date":"2026-03-11"},
  {"section":"Reading","path":"Reading/性别研究manuscript/性别研究manuscript.html","name":"性别研究manuscript.html","date":"2026-03-11"},
  {"section":"Reading","path":"Reading/RSAsupplementary/RSAsupplementary.html","name":"RSAsupplementary.html","date":"2026-03-14"},
  {"section":"Reading","path":"Reading/RSAmanuscript/RSAmanuscript.html","name":"RSAmanuscript.html","date":"2026-03-14"},
  {"section":"Reading","path":"Reading/supplementary/supplementary.html","name":"supplementary.html","date":"2026-03-11"},
  {"section":"Reading","path":"Reading/隔代supplementary/隔代supplementary.html","name":"隔代supplementary.html","date":"2026-03-16"},
  {"section":"Reading","path":"Reading/隔代manuscript/隔代manuscript.html","name":"隔代manuscript.html","date":"2026-03-16"},
  {"section":"Reading","path":"Reading/性别研究supplementary/性别研究supplementary.html","name":"性别研究supplementary.html","date":"2026-03-11"}
]
